MANIFEST.in
README
setup.cfg
setup.py
matialvarezs_charge_controller/__init__.py
matialvarezs_charge_controller/admin.py
matialvarezs_charge_controller/apps.py
matialvarezs_charge_controller/context_processors.py
matialvarezs_charge_controller/decorators.py
matialvarezs_charge_controller/definitions.py
matialvarezs_charge_controller/dispatcher.py
matialvarezs_charge_controller/errors.py
matialvarezs_charge_controller/managers.py
matialvarezs_charge_controller/middlewares.py
matialvarezs_charge_controller/models.py
matialvarezs_charge_controller/resend_data_to_server.py
matialvarezs_charge_controller/serializers.py
matialvarezs_charge_controller/settings.py
matialvarezs_charge_controller/signals.py
matialvarezs_charge_controller/tests.py
matialvarezs_charge_controller/urls.py
matialvarezs_charge_controller/utils.py
matialvarezs_charge_controller/views.py
matialvarezs_charge_controller.egg-info/PKG-INFO
matialvarezs_charge_controller.egg-info/SOURCES.txt
matialvarezs_charge_controller.egg-info/dependency_links.txt
matialvarezs_charge_controller.egg-info/requires.txt
matialvarezs_charge_controller.egg-info/top_level.txt
matialvarezs_charge_controller/api/urls.py
matialvarezs_charge_controller/api/v1/decorators.py
matialvarezs_charge_controller/api/v1/dispatcher.py
matialvarezs_charge_controller/api/v1/errors.py
matialvarezs_charge_controller/api/v1/urls.py
matialvarezs_charge_controller/api/v1/views.py
matialvarezs_charge_controller/github/client.py
matialvarezs_charge_controller/github/list_registers.py
matialvarezs_charge_controller/github/registers.py
matialvarezs_charge_controller/github/__pycache__/registers.cpython-35.pyc
matialvarezs_charge_controller/management/__init__.py
matialvarezs_charge_controller/management/__pycache__/__init__.cpython-35.pyc
matialvarezs_charge_controller/management/commands/__init__.py
matialvarezs_charge_controller/management/commands/matialvarezs_charge_controller_create_cronjob_delete_sent_local_data_to_server.py
matialvarezs_charge_controller/management/commands/matialvarezs_charge_controller_create_cronjob_send_data_to_server.py
matialvarezs_charge_controller/management/commands/matialvarezs_charge_controller_create_cronjob_send_local_data_to_server.py
