Metadata-Version: 1.1
Name: matialvarezs-charge-controller
Version: 0.0.149
Summary: Charge controller data
Home-page: UNKNOWN
Author: Matias Alvarez Sabate
Author-email: matialvarezs@gmail.com
License: UNKNOWN
Platform: UNKNOWN
Classifier: Programming Language :: Python :: 3.5
